{
  "entries": [
    {
      "start": "2017-10-10T11:00:00Z",
      "title": "First Event",
      "color": "#8c2b0e",
      "id": 1,
      "image": "https://trello-attachments.s3.amazonaws.com/59dfab8f98680de4b97ed197/59dfaddcb1cf0a29ce4c48bc/16a30013edf7a8cc8bbf797308285ae6/zebra.jpg",
      "content": "<p>Hallo World</p><blockquote>Quote</blockquote><ol><li>A</li><li>B</li><li>C</li></ol>"
    },
    {
      "start": "2017-10-20T06:00:00Z",
      "end": "2017-10-21T14:00:00Z",
      "title": "Second Event",
      "id": 2,
      "color": "#316509",
      "content": "",
      "image": ""
    },
    {
      "start": "2017-10-12",
      "end":"2017-10-26",
      "all_day": true,
      "image": "https://trello-attachments.s3.amazonaws.com/59dfab8f98680de4b97ed197/59dfaddcb1cf0a29ce4c48bc/16a30013edf7a8cc8bbf797308285ae6/zebra.jpg",
      "title": "Third Entry With Image And Some Very Long Text In The Title To See How It Is Handled",
      "content": "Content Here.",
      "id": 3
    },
    {
      "start": "2017-10-28T08:00:00Z",
      "end":"2017-10-28T20:00:00Z",
      "all_day": false,
      "image": "https://trello-attachments.s3.amazonaws.com/59dfab8f98680de4b97ed197/59dfaddcb1cf0a29ce4c48bc/16a30013edf7a8cc8bbf797308285ae6/zebra.jpg",
      "title": "Start & End",
      "content": "Content Here.",
      "color": "#777507",
      "id": 4
    }
  ]
}